yaap/__init__.py
yaap/argument.py
yaap/utils.py
yaap/yaap.py
yaap-0.4.2.dist-info/LICENSE
yaap-0.4.2.dist-info/METADATA
yaap-0.4.2.dist-info/WHEEL
yaap-0.4.2.dist-info/top_level.txt
yaap-0.4.2.dist-info/RECORD
