Metadata-Version: 2.1
Name: yaap
Version: 0.4.2
Summary: Yet another argument parser (Yaap)
Home-page: https://github.com/kaniblu/yaap
Author: Kang Min Yoo
Author-email: kangmin.yoo@gmail.com
License: UNKNOWN
Keywords: argument parser config file
Platform: UNKNOWN
Requires-Dist: pyyaml (==5.1.1)
Requires-Dist: jsonschema (==3.0.1)
